{ "candidates": [{"candidateId":"5957d4d3-2282-4788-b14e-287b8ceb8f89","constituencyId":"Ambur","name":"NAZAR MOHAMED.K","age":"49","sex":"Male","caste":"","party":"ADMK","telephone":"9790590135","email":"knazer70@gnail.com","officialProfileLink":"https://affidavit.eci.gov.in/show-profile/MjMxMg\u003d\u003d/MTY\u003d/MTA\u003d/Mw\u003d\u003d/QUM\u003d","officialPhotoLink":"none","socialMediaAccount":"","selfProfession":"Business / Tax Consultant","spouseProfession":"","highestEducationLevel":"Graduate BA, BBA, BSc, BBM","highestEducationYear":"1992","latestTaxReturn":{"self":{"year":"2019-2020","amount":"6,04,999"},"spouse":{"year":"2019-202","amount":"5,55,682"},"dependents":[{"year":"","amount":"","relation":""},{"year":"","amount":"","relation":""}]},"pendingCase":{"firNumber":"","policeStationName":"","section":"","briefDescription":"","caseNumber":"","courtName":"","chargesFramed":false,"dateOfChargesFramed":"","appealAgainstProceedings":false,"appealAgainstProceedingsDetails":"","appealAgainstPunishment":false},"convictedCase":{"section":"","briefDescription":"","caseNumber":"","courtName":"","chargesFramed":false,"appealAgainstProceedings":false,"convictionOrderDate":"","punishment":"","appealAgainstPunishment":false,"appealAgainstPunishmentDetails":""},"assets":{"movableSelf":{"amount":"31,84,362"},"movableSpouse":{"amount":"32,97,490"},"movableDependents":[{"amount":"","relation":""},{"amount":"","relation":""}],"immovableSelf":{"amount":"1,25,96,450"},"immovableSpouse":{"amount":"1,73,53,000"},"immovableDependents":[{"amount":"","relation":""},{"amount":"","relation":""}],"movableTotal":6481852,"immovableTotal":29949450,"candidateTotalAsset":36431302,"movableTotalString":"64,81,852","immovableTotalString":"2,99,49,450","candidateTotalAssetString":"3,64,31,302"},"liabilities":{"self":{"amount":""},"spouse":{"amount":""},"dependents":[{"amount":"","relation":""},{"amount":"","relation":""}],"candidateTotalLiability":0,"candidateTotalLiabilityString":"0"},"candidateTotalWealthString":"3,64,31,302","candidateTotalIncomeString":"11,60,681","candidateTotalWealth":36431302,"candidateTotalIncome":1160681}]}